skinport_console/__init__.py
skinport_console/cli.py
skinport_console-0.1.0.dist-info/METADATA
skinport_console-0.1.0.dist-info/WHEEL
skinport_console-0.1.0.dist-info/entry_points.txt
skinport_console-0.1.0.dist-info/licenses/LICENSE
skinport_console-0.1.0.dist-info/RECORD
